[
  {
    "model": "administration.legalpage",
    "pk": 1,
    "fields": {
      "page_type": "privacy",
      "title": "Politique de confidentialité",
      "content": "Dernière mise à jour : mars 2026\n\n1. RESPONSABLE DU TRAITEMENT\n\nInstantMusic, service en ligne de quiz musical multijoueur, est édité par [Nom de la société / NOM Prénom], dont le siège social est situé à [Adresse complète], ci-après désigné « l'Éditeur ».\n\nContact DPO / Responsable protection des données : [email@instantmusic.fr]\n\n2. DONNÉES COLLECTÉES\n\nNous collectons les données suivantes :\n\n- Données d'identification : nom d'utilisateur (pseudo), adresse e-mail (chiffrée en base), date d'inscription.\n- Données de jeu : historique des parties, scores, succès débloqués, classements.\n- Données de connexion : adresse IP, type de navigateur, horodatages de connexion.\n- Données de préférence : consentement aux cookies, paramètres de confidentialité.\n- En cas de connexion via Google OAuth : identifiant Google, adresse e-mail fournie par Google.\n\nNous ne collectons pas de données sensibles (santé, origine ethnique, opinions politiques, etc.).\n\n3. FINALITÉS DU TRAITEMENT\n\nVos données sont utilisées pour :\n\n- Créer et gérer votre compte utilisateur.\n- Permettre le fonctionnement du service (parties, classements, succès).\n- Assurer la sécurité et prévenir la fraude.\n- Vous envoyer des notifications liées au service (invitation à une partie, alertes de sécurité).\n- Améliorer nos services par analyse anonymisée de l'usage.\n\n4. BASE LÉGALE\n\n- Exécution du contrat (CGU) pour la fourniture du service.\n- Intérêt légitime pour la sécurité et la lutte contre la fraude.\n- Consentement pour les cookies analytiques et les communications marketing.\n\n5. DURÉE DE CONSERVATION\n\n- Données de compte : conservées pendant la durée du compte + 3 ans après sa suppression.\n- Données de jeu : conservées 5 ans.\n- Données de connexion : 12 mois.\n- Données de consentement : 5 ans.\n\n6. DESTINATAIRES DES DONNÉES\n\nVos données ne sont pas vendues. Elles peuvent être partagées avec :\n\n- Nos prestataires techniques hébergeant le service (serveurs UE).\n- Google LLC, dans le cadre de la connexion OAuth (soumis aux clauses contractuelles types).\n- Les autorités compétentes sur obligation légale.\n\nTout transfert hors UE est encadré par les garanties appropriées (clauses contractuelles types CE).\n\n7. VOS DROITS\n\nConformément au RGPD (règlement UE 2016/679), vous disposez des droits suivants :\n\n- Droit d'accès : obtenir une copie de vos données.\n- Droit de rectification : corriger des données inexactes.\n- Droit à l'effacement (« droit à l'oubli ») : demander la suppression de vos données.\n- Droit à la limitation du traitement : suspendre l'utilisation de vos données.\n- Droit à la portabilité : recevoir vos données dans un format structuré.\n- Droit d'opposition : vous opposer à un traitement basé sur l'intérêt légitime.\n- Droit de retrait du consentement : à tout moment, pour les traitements fondés sur ce consentement.\n\nPour exercer vos droits : [email@instantmusic.fr]\n\nVous pouvez également introduire une réclamation auprès de la CNIL (www.cnil.fr).\n\n8. COOKIES\n\nNous utilisons des cookies de session (nécessaires au fonctionnement), et optionnellement des cookies analytiques (avec consentement préalable). Pour plus d'informations, consultez notre bandeau de consentement.\n\n9. SÉCURITÉ\n\nNous mettons en œuvre des mesures techniques et organisationnelles appropriées : chiffrement des données sensibles, connexions HTTPS, contrôle d'accès, journalisation des accès.\n\n10. MODIFICATIONS\n\nNous nous réservons le droit de modifier cette politique. En cas de modification substantielle, vous en serez informé via le service. La date de dernière mise à jour figure en haut de cette page."
    }
  },
  {
    "model": "administration.legalpage",
    "pk": 2,
    "fields": {
      "page_type": "legal",
      "title": "Mentions légales",
      "content": "Conformément aux dispositions des articles 6-III et 19 de la Loi n°2004-575 du 21 juin 2004 pour la Confiance dans l'Économie Numérique, ci-après dite LCEN, il est porté à la connaissance des utilisateurs et visiteurs du site InstantMusic les présentes mentions légales.\n\n1. ÉDITEUR DU SITE\n\nRaison sociale : [Nom de la société ou NOM Prénom pour un particulier]\nStatut : [SAS / SARL / Auto-entrepreneur / Particulier]\nCapital social : [montant] €\nSiège social : [Adresse complète, Code Postal, Ville]\nRCS : [Ville d'immatriculation] [Numéro RCS]\nSIRET : [Numéro SIRET]\nCode APE : [Code APE]\nNuméro TVA intracommunautaire : [FR XX XXXXXXXXX]\n\nDirecteur de la publication : [NOM Prénom]\nContact : [email@instantmusic.fr]\n\n2. HÉBERGEMENT\n\nLe site InstantMusic est hébergé par :\n\n[Nom du fournisseur d'hébergement]\n[Adresse du fournisseur]\n[Téléphone]\n[Site web]\n\n3. PROPRIÉTÉ INTELLECTUELLE\n\nL'ensemble des contenus figurant sur le site (textes, images, logos, icônes, sons, logiciels) est la propriété exclusive de l'Éditeur ou fait l'objet d'une autorisation d'utilisation. Toute reproduction, représentation, modification, publication, adaptation totale ou partielle, quel que soit le moyen ou le procédé utilisé, est interdite, sauf autorisation écrite préalable de l'Éditeur.\n\nLes extraits musicaux proposés sur le service proviennent de l'API Deezer dans le cadre des conditions d'utilisation de cette API. Les droits sur ces extraits restent la propriété de leurs ayants droit respectifs.\n\n4. DONNÉES PERSONNELLES\n\nLes informations relatives à la collecte et au traitement des données personnelles sont détaillées dans notre Politique de confidentialité, accessible depuis le pied de page du site.\n\n5. COOKIES\n\nLe site peut utiliser des cookies. Vous pouvez configurer votre navigateur pour refuser les cookies ou être averti avant leur dépôt.\n\n6. LIMITATION DE RESPONSABILITÉ\n\nL'Éditeur s'efforce d'assurer la disponibilité et l'exactitude des informations présentes sur le site. Toutefois, il ne peut garantir que le service sera exempt d'erreurs, de bugs ou d'interruptions. L'Éditeur ne saurait être tenu responsable des dommages directs ou indirects résultant de l'utilisation du service.\n\n7. DROIT APPLICABLE ET JURIDICTION\n\nLes présentes mentions légales sont régies par le droit français. En cas de litige, et après tentative de résolution amiable, les tribunaux français seront seuls compétents.\n\n8. MÉDIATION\n\nConformément aux articles L.616-1 et R.616-1 du code de la consommation, nous proposons un dispositif de médiation de la consommation. L'entité de médiation retenue est : [Nom du médiateur]. En cas de litige, vous pouvez déposer votre réclamation sur son site : [URL du médiateur]."
    }
  }
]
